Workbook

Sheet Cover
A2: MICROSOFT CORPORATION Equity Valuation & Sensitivity Analysis DCF Model | FY2024A – FY2029E
A8: Prepared: May 2026 | Currency: USD Millions | Ticker: MSFT | Exchange: NASDAQ
B11: TABLE OF CONTENTS
B12: Tab | C12: Sheet Name | D12: Description
B13: 1 | C13: Assumptions | D13: Key inputs, growth rates, margins, valuation parameters
B14: 2 | C14: Income Statement | D14: 5-year P&L projection: Revenue → EBITDA → Net Income
B15: 3 | C15: Cash Flow Statement | D15: CFO, Capex, and Free Cash Flow to Firm (FCFF)
B16: 4 | C16: DCF Valuation | D16: Discounted FCFF + Terminal Value → Enterprise & Equity Value
B17: 5 | C17: Sensitivity Analysis | D17: Three 2D heat-map tables: WACC × Multiple, Growth × WACC, COGS × Multiple
B18: 6 | C18: Charts & Visualizations | D18: Revenue, EBITDA, margin progression, and FCFF trend charts
B19: 7 | C19: Tornado Analysis | D19: Ranked single-variable sensitivity and horizontal tornado chart
B23: BASE CASE KEY METRICS
B24: Metric | C24: Value | D24: Note
B25: FY2024 Revenue | C25: $245B | D25: Actual reported
B26: FY2029E Revenue (proj) | C26: ~$430B | D26: at 12-16% CAGR
B27: Base WACC | C27: 9.5% | D27: Blended cost of capital
B28: EV/EBITDA Exit | C28: 28.0x | D28: In-line with tech peer median
B29: Tax Rate | C29: 21.0% | D29: Effective blended rate
B30: Implied Share Price | C30: See DCF | D30: Varies by scenario
A35: DISCLAIMER: This model is for educational and analytical purposes only. All projections are estimates based on publicly available information and analyst consensus. This does not constitute investment advice. Past performance is not indicative of future results.

Sheet Assumptions
A1: MICROSOFT CORPORATION | EQUITY VALUATION MODEL
A2: Key Assumptions & Input Dashboard | All figures in USD Millions unless stated
A4: 📋 COLOR LEGEND
B5: Blue text = Hardcoded input (edit these cells)
B6: Black text = Formula / calculated value
B7: Yellow background = Key assumption cell
A9: 📈 REVENUE GROWTH ASSUMPTIONS
B10: Assumption | C10: FY2025E | D10: FY2026E | E10: FY2027E | F10: FY2028E | G10: FY2029E
B11: Revenue Growth Rate | C11: ='Tornado Analysis'!J21+'Tornado Analysis'!B28 -> 0.15 | D11: =C11+1% -> 0.16 | E11: =C11-1% -> 0.14 | F11: =C11-2% -> 0.13 | G11: =C11-3% -> 0.12
A13: 💰 MARGIN ASSUMPTIONS
B14: Assumption | C14: FY2025E | D14: FY2026E | E14: FY2027E | F14: FY2028E | G14: FY2029E
B15: COGS as % of Revenue | C15: =33%+'Tornado Analysis'!E28 -> 0.33 | D15: =32.5%+'Tornado Analysis'!E28 -> 0.325 | E15: =32%+'Tornado Analysis'!E28 -> 0.32 | F15: =31.5%+'Tornado Analysis'!E28 -> 0.315 | G15: =31%+'Tornado Analysis'!E28 -> 0.31
B16: R&D as % of Revenue | C16: 0.115 | D16: 0.112 | E16: 0.11 | F16: 0.108 | G16: 0.106
B17: SG&A as % of Revenue | C17: 0.085 | D17: 0.083 | E17: 0.081 | F17: 0.079 | G17: 0.077
B18: D&A as % of Revenue | C18: 0.052 | D18: 0.053 | E18: 0.054 | F18: 0.054 | G18: 0.055
B19: Capex as % of Revenue | C19: 0.09 | D19: 0.092 | E19: 0.09 | F19: 0.088 | G19: 0.086
B20: Change in NWC as % Rev Chg | C20: 0.05 | D20: 0.05 | E20: 0.05 | F20: 0.05 | G20: 0.05
A22: 🎯 VALUATION & DCF ASSUMPTIONS
B23: Parameter | C23: Value | D23: Notes
B24: Tax Rate | C24: 0.21 | D24: Effective blended rate
B25: WACC / Discount Rate | C25: =9.5%+'Tornado Analysis'!L28 -> 0.095 | D25: Weighted avg cost of capital
B26: Terminal Growth Rate | C26: =3%+'Tornado Analysis'!O28 -> 0.03 | D26: Long-run nominal GDP growth
B27: EV / EBITDA Exit Multiple | C27: ='Tornado Analysis'!J22 -> 28 | D27: FY2029 exit multiple
B28: Shares Outstanding (mm) | C28: 7435 | D28: Diluted shares as of FY2024
B29: Net Debt / (Cash) ($mm) | C29: -20000 | D29: Negative = net cash

Sheet Income Statement
A1: MICROSOFT CORPORATION | INCOME STATEMENT | USD Millions
C3: FY2024A | D3: FY2025E | E3: FY2026E | F3: FY2027E | G3: FY2028E | H3: FY2029E
C4: Actual | D4: Projected | E4: Projected | F4: Projected | G4: Projected | H4: Projected
B5: REVENUE
B6: Revenue | C6: 245122 | D6: =C6*(1+Assumptions!C11) -> 281890.3 | E6: =D6*(1+Assumptions!D11) -> 326992.75 | F6: =E6*(1+Assumptions!E11) -> 372771.73 | G6: =F6*(1+Assumptions!F11) -> 421232.06 | H6: =G6*(1+Assumptions!G11) -> 471779.9
B7: COSTS
B8: Cost of Revenue (COGS) | C8: 74114 | D8: =-D6*Assumptions!C15 -> -93023.799 | E8: =-E6*Assumptions!D15 -> -106272.64 | F8: =-F6*Assumptions!E15 -> -119286.95 | G8: =-G6*Assumptions!F15 -> -132688.1 | H8: =-H6*Assumptions!G15 -> -146251.77
B9: Gross Profit | C9: =C6+C8 -> 319236 | D9: =D6+D8 -> 188866.5 | E9: =E6+E8 -> 220720.1 | F9: =F6+F8 -> 253484.78 | G9: =G6+G8 -> 288543.96 | H9: =H6+H8 -> 325528.13
B10: Gross Margin % | C10: =IF(C6=0,0,C9/C6) -> 1.3023556 | D10: =IF(D6=0,0,D9/D6) -> 0.67 | E10: =IF(E6=0,0,E9/E6) -> 0.675 | F10: =IF(F6=0,0,F9/F6) -> 0.68 | G10: =IF(G6=0,0,G9/G6) -> 0.685 | H10: =IF(H6=0,0,H9/H6) -> 0.69
B11: Research & Development | C11: -29510 | D11: =-D6*Assumptions!C16 -> -32417.385 | E11: =-E6*Assumptions!D16 -> -36623.188 | F11: =-F6*Assumptions!E16 -> -41004.891 | G11: =-G6*Assumptions!F16 -> -45493.062 | H11: =-H6*Assumptions!G16 -> -50008.67
B12: Selling, General & Administrative | C12: -24456 | D12: =-D6*Assumptions!C17 -> -23960.676 | E12: =-E6*Assumptions!D17 -> -27140.398 | F12: =-F6*Assumptions!E17 -> -30194.51 | G12: =-G6*Assumptions!F17 -> -33277.333 | H12: =-H6*Assumptions!G17 -> -36327.053
B13: Operating Income (EBIT) | C13: =C9+C11+C12 -> 265270 | D13: =D9+D11+D12 -> 132488.44 | E13: =E9+E11+E12 -> 156956.52 | F13: =F9+F11+F12 -> 182285.38 | G13: =G9+G11+G12 -> 209773.56 | H13: =H9+H11+H12 -> 239192.41
B14: EBIT Margin % | C14: =IF(C6=0,0,C13/C6) -> 1.0821958 | D14: =IF(D6=0,0,D13/D6) -> 0.47 | E14: =IF(E6=0,0,E13/E6) -> 0.48 | F14: =IF(F6=0,0,F13/F6) -> 0.489 | G14: =IF(G6=0,0,G13/G6) -> 0.498 | H14: =IF(H6=0,0,H13/H6) -> 0.507
B15: Depreciation & Amortization (add-back) | C15: 13866 | D15: =D6*Assumptions!C18 -> 14658.296 | E15: =E6*Assumptions!D18 -> 17330.616 | F15: =F6*Assumptions!E18 -> 20129.674 | G15: =G6*Assumptions!F18 -> 22746.531 | H15: =H6*Assumptions!G18 -> 25947.895
B16: EBITDA | C16: =C13+C15 -> 279136 | D16: =D13+D15 -> 147146.74 | E16: =E13+E15 -> 174287.13 | F16: =F13+F15 -> 202415.05 | G16: =G13+G15 -> 232520.1 | H16: =H13+H15 -> 265140.31
B17: BELOW THE LINE
B18: Interest Income & Other, net | C18: 3269 | D18: 3500 | E18: 3500 | F18: 3500 | G18: 3500 | H18: 3500
B19: Pre-Tax Income | C19: =C13+C18 -> 268539 | D19: =D13+D18 -> 135988.44 | E19: =E13+E18 -> 160456.52 | F19: =F13+F18 -> 185785.38 | G19: =G13+G18 -> 213273.56 | H19: =H13+H18 -> 242692.41
B20: Income Tax Provision | C20: =-C19*Assumptions!C24 -> -56393.19 | D20: =-D19*Assumptions!C24 -> -28557.573 | E20: =-E19*Assumptions!C24 -> -33695.869 | F20: =-F19*Assumptions!C24 -> -39014.929 | G20: =-G19*Assumptions!C24 -> -44787.449 | H20: =-H19*Assumptions!C24 -> -50965.406
B21: Net Income | C21: =C19+C20 -> 212145.81 | D21: =D19+D20 -> 107430.87 | E21: =E19+E20 -> 126760.65 | F21: =F19+F20 -> 146770.45 | G21: =G19+G20 -> 168486.12 | H21: =H19+H20 -> 191727.01
B22: Net Margin % | C22: =IF(C6=0,0,C21/C6) -> 0.8654703 | D22: =IF(D6=0,0,D21/D6) -> 0.38110878 | E22: =IF(E6=0,0,E21/E6) -> 0.38765585 | F22: =IF(F6=0,0,F21/F6) -> 0.39372741 | G22: =IF(G6=0,0,G21/G6) -> 0.39998408 | H22: =IF(H6=0,0,H21/H6) -> 0.40639078

Sheet Cash Flow Statement
A1: MICROSOFT CORPORATION | CASH FLOW STATEMENT | USD Millions
C3: FY2024A | D3: FY2025E | E3: FY2026E | F3: FY2027E | G3: FY2028E | H3: FY2029E
B4: OPERATING ACTIVITIES
B5: Net Income | C5: ='Income Statement'!C21 -> 212145.81 | D5: ='Income Statement'!D21 -> 107430.87 | E5: ='Income Statement'!E21 -> 126760.65 | F5: ='Income Statement'!F21 -> 146770.45 | G5: ='Income Statement'!G21 -> 168486.12 | H5: ='Income Statement'!H21 -> 191727.01
B6: (+) Depreciation & Amortization | C6: ='Income Statement'!C15 -> 13866 | D6: ='Income Statement'!D15 -> 14658.296 | E6: ='Income Statement'!E15 -> 17330.616 | F6: ='Income Statement'!F15 -> 20129.674 | G6: ='Income Statement'!G15 -> 22746.531 | H6: ='Income Statement'!H15 -> 25947.895
B7: (-) Increase in Net Working Capital | C7: -2500 | D7: =-('Income Statement'!D6-'Income Statement'!C6)*Assumptions!C20 -> -1838.415 | E7: =-('Income Statement'!E6-'Income Statement'!D6)*Assumptions!D20 -> -2255.1224 | F7: =-('Income Statement'!F6-'Income Statement'!E6)*Assumptions!E20 -> -2288.9492 | G7: =-('Income Statement'!G6-'Income Statement'!F6)*Assumptions!F20 -> -2423.0163 | H7: =-('Income Statement'!H6-'Income Statement'!G6)*Assumptions!G20 -> -2527.3923
B8: (+) Other Operating Adjustments | C8: 2000 | D8: 2000 | E8: 2000 | F8: 2000 | G8: 2000 | H8: 2000
B9: Cash from Operations | C9: =SUM(C5:C8) -> 225511.81 | D9: =SUM(D5:D8) -> 122250.75 | E9: =SUM(E5:E8) -> 143836.14 | F9: =SUM(F5:F8) -> 166611.17 | G9: =SUM(G5:G8) -> 190809.63 | H9: =SUM(H5:H8) -> 217147.51
B10: INVESTING ACTIVITIES
B11: Capital Expenditures | C11: -44482 | D11: =-'Income Statement'!D6*Assumptions!C19 -> -25370.127 | E11: =-'Income Statement'!E6*Assumptions!D19 -> -30083.333 | F11: =-'Income Statement'!F6*Assumptions!E19 -> -33549.456 | G11: =-'Income Statement'!G6*Assumptions!F19 -> -37068.421 | H11: =-'Income Statement'!H6*Assumptions!G19 -> -40573.072
B12: Cash used in Investing (Capex only) | C12: =C11 -> -44482 | D12: =D11 -> -25370.127 | E12: =E11 -> -30083.333 | F12: =F11 -> -33549.456 | G12: =G11 -> -37068.421 | H12: =H11 -> -40573.072
B13: FREE CASH FLOW TO FIRM (FCFF)
B14: FCFF (Unlevered Free Cash Flow) | C14: =C9+C11 -> 181029.81 | D14: =D9+D11 -> 96880.622 | E14: =E9+E11 -> 113752.81 | F14: =F9+F11 -> 133061.72 | G14: =G9+G11 -> 153741.21 | H14: =H9+H11 -> 176574.44

Sheet DCF Valuation
A1: MICROSOFT CORPORATION | DCF VALUATION | USD Millions
C3: FY2025E | D3: FY2026E | E3: FY2027E | F3: FY2028E | G3: FY2029E
B4: STEP 1: DISCOUNTED FREE CASH FLOWS
B5: Unlevered Free Cash Flow (FCFF) | C5: ='Cash Flow Statement'!D14 -> 96880.622 | D5: ='Cash Flow Statement'!E14 -> 113752.81 | E5: ='Cash Flow Statement'!F14 -> 133061.72 | F5: ='Cash Flow Statement'!G14 -> 153741.21 | G5: ='Cash Flow Statement'!H14 -> 176574.44
B6: Discount Factor [1/(1+WACC)^t] | C6: =1/(1+Assumptions!C25)^1 -> 0.91324201 | D6: =1/(1+Assumptions!C25)^2 -> 0.83401097 | E6: =1/(1+Assumptions!C25)^3 -> 0.76165385 | F6: =1/(1+Assumptions!C25)^4 -> 0.69557429 | G6: =1/(1+Assumptions!C25)^5 -> 0.63522767
B7: PV of FCFF | C7: =C5*C6 -> 88475.454 | D7: =D5*D6 -> 94871.091 | E7: =E5*E6 -> 101346.97 | F7: =F5*F6 -> 106938.43 | G7: =G5*G6 -> 112164.97
B8: STEP 2: TERMINAL VALUE (Dual Method)
B9: FY2029 EBITDA (terminal year) | C9: ='Income Statement'!H16 -> 265140.31
B10: Terminal Value — EV/EBITDA Method | C10: =C9*('Tornado Analysis'!J22+'Tornado Analysis'!H28) -> 7423928.6
B11: PV of Terminal Value (EV/EBITDA) | C11: =C10/(1+Assumptions!C25)^5 -> 4715884.8
B12: Terminal Value — Gordon Growth Crosscheck | C12: ='Cash Flow Statement'!H14*(1+Assumptions!C26)/(Assumptions!C25-Assumptions!C26) -> 2798025.7
B13: PV of Terminal Value (Gordon Growth) | C13: =C12/(1+Assumptions!C25)^5 -> 1777383.3
B16: STEP 3: EQUITY VALUE BRIDGE
B17: Sum of PV of FCFFs (FY25-FY29) | C17: =SUM(C7:G7) -> 503796.91
B18: (+) PV of Terminal Value (EV/EBITDA) | C18: =C11 -> 4715884.8
B19: Enterprise Value | C19: =C17+C18 -> 5219681.7
B20: (-) Net Debt / (+) Net Cash | C20: =Assumptions!C29 -> -20000
B21: Equity Value | C21: =C19-C20 -> 5239681.7
B22: Diluted Shares Outstanding (mm) | C22: =Assumptions!C28 -> 7435
B23: ★ IMPLIED SHARE PRICE ★ | C23: =C21/C22 -> 704.73191
B24: Current Market Price (for reference) | C24: 450
B25: Implied Upside / (Downside) | C25: =C23/C24-1 -> 0.56607091

Sheet Sensitivity Analysis
A1: MICROSOFT CORPORATION | SENSITIVITY ANALYSIS | Implied Share Price ($)
A2: Each table shows implied share price as two key drivers vary simultaneously — holding all other assumptions at base case
B5: TABLE 1: Share Price Sensitivity — WACC vs. EV/EBITDA Multiple
B6: WACC ↓ / EV/EBITDA → | C6: 20x | D6: 22x | E6: 24x | F6: 26x | G6: 28x | H6: 30x | I6: 32x | J6: 34x
B7: 7.5% | C7: =('Cash Flow Statement'!D14*(1/(1+0.075)^1)+'Cash Flow Statement'!E14*(1/(1+0.075)^2)+'Cash Flow Statement'!F14*(1/(1+0.075)^3)+'Cash Flow Statement'!G14*(1/(1+0.075)^4)+'Cash Flow Statement'!H14*(1/(1+0.075)^5)+('Income Statement'!H16*20)/(1+0.075)^5-Assumptions!C29)/Assumptions!C28 -> 571.28397 | D7: =('Cash Flow Statement'!D14*(1/(1+0.075)^1)+'Cash Flow Statement'!E14*(1/(1+0.075)^2)+'Cash Flow Statement'!F14*(1/(1+0.075)^3)+'Cash Flow Statement'!G14*(1/(1+0.075)^4)+'Cash Flow Statement'!H14*(1/(1+0.075)^5)+('Income Statement'!H16*22)/(1+0.075)^5-Assumptions!C29)/Assumptions!C28 -> 620.96407 | E7: =('Cash Flow Statement'!D14*(1/(1+0.075)^1)+'Cash Flow Statement'!E14*(1/(1+0.075)^2)+'Cash Flow Statement'!F14*(1/(1+0.075)^3)+'Cash Flow Statement'!G14*(1/(1+0.075)^4)+'Cash Flow Statement'!H14*(1/(1+0.075)^5)+('Income Statement'!H16*24)/(1+0.075)^5-Assumptions!C29)/Assumptions!C28 -> 670.64417 | F7: =('Cash Flow Statement'!D14*(1/(1+0.075)^1)+'Cash Flow Statement'!E14*(1/(1+0.075)^2)+'Cash Flow Statement'!F14*(1/(1+0.075)^3)+'Cash Flow Statement'!G14*(1/(1+0.075)^4)+'Cash Flow Statement'!H14*(1/(1+0.075)^5)+('Income Statement'!H16*26)/(1+0.075)^5-Assumptions!C29)/Assumptions!C28 -> 720.32426 | G7: =('Cash Flow Statement'!D14*(1/(1+0.075)^1)+'Cash Flow Statement'!E14*(1/(1+0.075)^2)+'Cash Flow Statement'!F14*(1/(1+0.075)^3)+'Cash Flow Statement'!G14*(1/(1+0.075)^4)+'Cash Flow Statement'!H14*(1/(1+0.075)^5)+('Income Statement'!H16*28)/(1+0.075)^5-Assumptions!C29)/Assumptions!C28 -> 770.00436 | H7: =('Cash Flow Statement'!D14*(1/(1+0.075)^1)+'Cash Flow Statement'!E14*(1/(1+0.075)^2)+'Cash Flow Statement'!F14*(1/(1+0.075)^3)+'Cash Flow Statement'!G14*(1/(1+0.075)^4)+'Cash Flow Statement'!H14*(1/(1+0.075)^5)+('Income Statement'!H16*30)/(1+0.075)^5-Assumptions!C29)/Assumptions!C28 -> 819.68446 | I7: =('Cash Flow Statement'!D14*(1/(1+0.075)^1)+'Cash Flow Statement'!E14*(1/(1+0.075)^2)+'Cash Flow Statement'!F14*(1/(1+0.075)^3)+'Cash Flow Statement'!G14*(1/(1+0.075)^4)+'Cash Flow Statement'!H14*(1/(1+0.075)^5)+('Income Statement'!H16*32)/(1+0.075)^5-Assumptions!C29)/Assumptions!C28 -> 869.36456 | J7: =('Cash Flow Statement'!D14*(1/(1+0.075)^1)+'Cash Flow Statement'!E14*(1/(1+0.075)^2)+'Cash Flow Statement'!F14*(1/(1+0.075)^3)+'Cash Flow Statement'!G14*(1/(1+0.075)^4)+'Cash Flow Statement'!H14*(1/(1+0.075)^5)+('Income Statement'!H16*34)/(1+0.075)^5-Assumptions!C29)/Assumptions!C28 -> 919.04466
B8: 8.0% | C8: =('Cash Flow Statement'!D14*(1/(1+0.08)^1)+'Cash Flow Statement'!E14*(1/(1+0.08)^2)+'Cash Flow Statement'!F14*(1/(1+0.08)^3)+'Cash Flow Statement'!G14*(1/(1+0.08)^4)+'Cash Flow Statement'!H14*(1/(1+0.08)^5)+('Income Statement'!H16*20)/(1+0.08)^5-Assumptions!C29)/Assumptions!C28 -> 558.8482 | D8: =('Cash Flow Statement'!D14*(1/(1+0.08)^1)+'Cash Flow Statement'!E14*(1/(1+0.08)^2)+'Cash Flow Statement'!F14*(1/(1+0.08)^3)+'Cash Flow Statement'!G14*(1/(1+0.08)^4)+'Cash Flow Statement'!H14*(1/(1+0.08)^5)+('Income Statement'!H16*22)/(1+0.08)^5-Assumptions!C29)/Assumptions!C28 -> 607.3889 | E8: =('Cash Flow Statement'!D14*(1/(1+0.08)^1)+'Cash Flow Statement'!E14*(1/(1+0.08)^2)+'Cash Flow Statement'!F14*(1/(1+0.08)^3)+'Cash Flow Statement'!G14*(1/(1+0.08)^4)+'Cash Flow Statement'!H14*(1/(1+0.08)^5)+('Income Statement'!H16*24)/(1+0.08)^5-Assumptions!C29)/Assumptions!C28 -> 655.92959 | F8: =('Cash Flow Statement'!D14*(1/(1+0.08)^1)+'Cash Flow Statement'!E14*(1/(1+0.08)^2)+'Cash Flow Statement'!F14*(1/(1+0.08)^3)+'Cash Flow Statement'!G14*(1/(1+0.08)^4)+'Cash Flow Statement'!H14*(1/(1+0.08)^5)+('Income Statement'!H16*26)/(1+0.08)^5-Assumptions!C29)/Assumptions!C28 -> 704.47029 | G8: =('Cash Flow Statement'!D14*(1/(1+0.08)^1)+'Cash Flow Statement'!E14*(1/(1+0.08)^2)+'Cash Flow Statement'!F14*(1/(1+0.08)^3)+'Cash Flow Statement'!G14*(1/(1+0.08)^4)+'Cash Flow Statement'!H14*(1/(1+0.08)^5)+('Income Statement'!H16*28)/(1+0.08)^5-Assumptions!C29)/Assumptions!C28 -> 753.01099 | H8: =('Cash Flow Statement'!D14*(1/(1+0.08)^1)+'Cash Flow Statement'!E14*(1/(1+0.08)^2)+'Cash Flow Statement'!F14*(1/(1+0.08)^3)+'Cash Flow Statement'!G14*(1/(1+0.08)^4)+'Cash Flow Statement'!H14*(1/(1+0.08)^5)+('Income Statement'!H16*30)/(1+0.08)^5-Assumptions!C29)/Assumptions!C28 -> 801.55168 | I8: =('Cash Flow Statement'!D14*(1/(1+0.08)^1)+'Cash Flow Statement'!E14*(1/(1+0.08)^2)+'Cash Flow Statement'!F14*(1/(1+0.08)^3)+'Cash Flow Statement'!G14*(1/(1+0.08)^4)+'Cash Flow Statement'!H14*(1/(1+0.08)^5)+('Income Statement'!H16*32)/(1+0.08)^5-Assumptions!C29)/Assumptions!C28 -> 850.09238 | J8: =('Cash Flow Statement'!D14*(1/(1+0.08)^1)+'Cash Flow Statement'!E14*(1/(1+0.08)^2)+'Cash Flow Statement'!F14*(1/(1+0.08)^3)+'Cash Flow Statement'!G14*(1/(1+0.08)^4)+'Cash Flow Statement'!H14*(1/(1+0.08)^5)+('Income Statement'!H16*34)/(1+0.08)^5-Assumptions!C29)/Assumptions!C28 -> 898.63307
B9: 8.5% | C9: =('Cash Flow Statement'!D14*(1/(1+0.085)^1)+'Cash Flow Statement'!E14*(1/(1+0.085)^2)+'Cash Flow Statement'!F14*(1/(1+0.085)^3)+'Cash Flow Statement'!G14*(1/(1+0.085)^4)+'Cash Flow Statement'!H14*(1/(1+0.085)^5)+('Income Statement'!H16*20)/(1+0.085)^5-Assumptions!C29)/Assumptions!C28 -> 546.74736 | D9: =('Cash Flow Statement'!D14*(1/(1+0.085)^1)+'Cash Flow Statement'!E14*(1/(1+0.085)^2)+'Cash Flow Statement'!F14*(1/(1+0.085)^3)+'Cash Flow Statement'!G14*(1/(1+0.085)^4)+'Cash Flow Statement'!H14*(1/(1+0.085)^5)+('Income Statement'!H16*22)/(1+0.085)^5-Assumptions!C29)/Assumptions!C28 -> 594.17986 | E9: =('Cash Flow Statement'!D14*(1/(1+0.085)^1)+'Cash Flow Statement'!E14*(1/(1+0.085)^2)+'Cash Flow Statement'!F14*(1/(1+0.085)^3)+'Cash Flow Statement'!G14*(1/(1+0.085)^4)+'Cash Flow Statement'!H14*(1/(1+0.085)^5)+('Income Statement'!H16*24)/(1+0.085)^5-Assumptions!C29)/Assumptions!C28 -> 641.61237 | F9: =('Cash Flow Statement'!D14*(1/(1+0.085)^1)+'Cash Flow Statement'!E14*(1/(1+0.085)^2)+'Cash Flow Statement'!F14*(1/(1+0.085)^3)+'Cash Flow Statement'!G14*(1/(1+0.085)^4)+'Cash Flow Statement'!H14*(1/(1+0.085)^5)+('Income Statement'!H16*26)/(1+0.085)^5-Assumptions!C29)/Assumptions!C28 -> 689.04488 | G9: =('Cash Flow Statement'!D14*(1/(1+0.085)^1)+'Cash Flow Statement'!E14*(1/(1+0.085)^2)+'Cash Flow Statement'!F14*(1/(1+0.085)^3)+'Cash Flow Statement'!G14*(1/(1+0.085)^4)+'Cash Flow Statement'!H14*(1/(1+0.085)^5)+('Income Statement'!H16*28)/(1+0.085)^5-Assumptions!C29)/Assumptions!C28 -> 736.47739 | H9: =('Cash Flow Statement'!D14*(1/(1+0.085)^1)+'Cash Flow Statement'!E14*(1/(1+0.085)^2)+'Cash Flow Statement'!F14*(1/(1+0.085)^3)+'Cash Flow Statement'!G14*(1/(1+0.085)^4)+'Cash Flow Statement'!H14*(1/(1+0.085)^5)+('Income Statement'!H16*30)/(1+0.085)^5-Assumptions!C29)/Assumptions!C28 -> 783.90989 | I9: =('Cash Flow Statement'!D14*(1/(1+0.085)^1)+'Cash Flow Statement'!E14*(1/(1+0.085)^2)+'Cash Flow Statement'!F14*(1/(1+0.085)^3)+'Cash Flow Statement'!G14*(1/(1+0.085)^4)+'Cash Flow Statement'!H14*(1/(1+0.085)^5)+('Income Statement'!H16*32)/(1+0.085)^5-Assumptions!C29)/Assumptions!C28 -> 831.3424 | J9: =('Cash Flow Statement'!D14*(1/(1+0.085)^1)+'Cash Flow Statement'!E14*(1/(1+0.085)^2)+'Cash Flow Statement'!F14*(1/(1+0.085)^3)+'Cash Flow Statement'!G14*(1/(1+0.085)^4)+'Cash Flow Statement'!H14*(1/(1+0.085)^5)+('Income Statement'!H16*34)/(1+0.085)^5-Assumptions!C29)/Assumptions!C28 -> 878.77491
B10: 9.0% | C10: =('Cash Flow Statement'!D14*(1/(1+0.09)^1)+'Cash Flow Statement'!E14*(1/(1+0.09)^2)+'Cash Flow Statement'!F14*(1/(1+0.09)^3)+'Cash Flow Statement'!G14*(1/(1+0.09)^4)+'Cash Flow Statement'!H14*(1/(1+0.09)^5)+('Income Statement'!H16*20)/(1+0.09)^5-Assumptions!C29)/Assumptions!C28 -> 534.97087 | D10: =('Cash Flow Statement'!D14*(1/(1+0.09)^1)+'Cash Flow Statement'!E14*(1/(1+0.09)^2)+'Cash Flow Statement'!F14*(1/(1+0.09)^3)+'Cash Flow Statement'!G14*(1/(1+0.09)^4)+'Cash Flow Statement'!H14*(1/(1+0.09)^5)+('Income Statement'!H16*22)/(1+0.09)^5-Assumptions!C29)/Assumptions!C28 -> 581.32541 | E10: =('Cash Flow Statement'!D14*(1/(1+0.09)^1)+'Cash Flow Statement'!E14*(1/(1+0.09)^2)+'Cash Flow Statement'!F14*(1/(1+0.09)^3)+'Cash Flow Statement'!G14*(1/(1+0.09)^4)+'Cash Flow Statement'!H14*(1/(1+0.09)^5)+('Income Statement'!H16*24)/(1+0.09)^5-Assumptions!C29)/Assumptions!C28 -> 627.67995 | F10: =('Cash Flow Statement'!D14*(1/(1+0.09)^1)+'Cash Flow Statement'!E14*(1/(1+0.09)^2)+'Cash Flow Statement'!F14*(1/(1+0.09)^3)+'Cash Flow Statement'!G14*(1/(1+0.09)^4)+'Cash Flow Statement'!H14*(1/(1+0.09)^5)+('Income Statement'!H16*26)/(1+0.09)^5-Assumptions!C29)/Assumptions!C28 -> 674.03449 | G10: =('Cash Flow Statement'!D14*(1/(1+0.09)^1)+'Cash Flow Statement'!E14*(1/(1+0.09)^2)+'Cash Flow Statement'!F14*(1/(1+0.09)^3)+'Cash Flow Statement'!G14*(1/(1+0.09)^4)+'Cash Flow Statement'!H14*(1/(1+0.09)^5)+('Income Statement'!H16*28)/(1+0.09)^5-Assumptions!C29)/Assumptions!C28 -> 720.38903 | H10: =('Cash Flow Statement'!D14*(1/(1+0.09)^1)+'Cash Flow Statement'!E14*(1/(1+0.09)^2)+'Cash Flow Statement'!F14*(1/(1+0.09)^3)+'Cash Flow Statement'!G14*(1/(1+0.09)^4)+'Cash Flow Statement'!H14*(1/(1+0.09)^5)+('Income Statement'!H16*30)/(1+0.09)^5-Assumptions!C29)/Assumptions!C28 -> 766.74357 | I10: =('Cash Flow Statement'!D14*(1/(1+0.09)^1)+'Cash Flow Statement'!E14*(1/(1+0.09)^2)+'Cash Flow Statement'!F14*(1/(1+0.09)^3)+'Cash Flow Statement'!G14*(1/(1+0.09)^4)+'Cash Flow Statement'!H14*(1/(1+0.09)^5)+('Income Statement'!H16*32)/(1+0.09)^5-Assumptions!C29)/Assumptions!C28 -> 813.09811 | J10: =('Cash Flow Statement'!D14*(1/(1+0.09)^1)+'Cash Flow Statement'!E14*(1/(1+0.09)^2)+'Cash Flow Statement'!F14*(1/(1+0.09)^3)+'Cash Flow Statement'!G14*(1/(1+0.09)^4)+'Cash Flow Statement'!H14*(1/(1+0.09)^5)+('Income Statement'!H16*34)/(1+0.09)^5-Assumptions!C29)/Assumptions!C28 -> 859.45265
B11: 9.5% | C11: =('Cash Flow Statement'!D14*(1/(1+0.095)^1)+'Cash Flow Statement'!E14*(1/(1+0.095)^2)+'Cash Flow Statement'!F14*(1/(1+0.095)^3)+'Cash Flow Statement'!G14*(1/(1+0.095)^4)+'Cash Flow Statement'!H14*(1/(1+0.095)^5)+('Income Statement'!H16*20)/(1+0.095)^5-Assumptions!C29)/Assumptions!C28 -> 523.50855 | D11: =('Cash Flow Statement'!D14*(1/(1+0.095)^1)+'Cash Flow Statement'!E14*(1/(1+0.095)^2)+'Cash Flow Statement'!F14*(1/(1+0.095)^3)+'Cash Flow Statement'!G14*(1/(1+0.095)^4)+'Cash Flow Statement'!H14*(1/(1+0.095)^5)+('Income Statement'!H16*22)/(1+0.095)^5-Assumptions!C29)/Assumptions!C28 -> 568.81439 | E11: =('Cash Flow Statement'!D14*(1/(1+0.095)^1)+'Cash Flow Statement'!E14*(1/(1+0.095)^2)+'Cash Flow Statement'!F14*(1/(1+0.095)^3)+'Cash Flow Statement'!G14*(1/(1+0.095)^4)+'Cash Flow Statement'!H14*(1/(1+0.095)^5)+('Income Statement'!H16*24)/(1+0.095)^5-Assumptions!C29)/Assumptions!C28 -> 614.12023 | F11: =('Cash Flow Statement'!D14*(1/(1+0.095)^1)+'Cash Flow Statement'!E14*(1/(1+0.095)^2)+'Cash Flow Statement'!F14*(1/(1+0.095)^3)+'Cash Flow Statement'!G14*(1/(1+0.095)^4)+'Cash Flow Statement'!H14*(1/(1+0.095)^5)+('Income Statement'!H16*26)/(1+0.095)^5-Assumptions!C29)/Assumptions!C28 -> 659.42607 | G11: =('Cash Flow Statement'!D14*(1/(1+0.095)^1)+'Cash Flow Statement'!E14*(1/(1+0.095)^2)+'Cash Flow Statement'!F14*(1/(1+0.095)^3)+'Cash Flow Statement'!G14*(1/(1+0.095)^4)+'Cash Flow Statement'!H14*(1/(1+0.095)^5)+('Income Statement'!H16*28)/(1+0.095)^5-Assumptions!C29)/Assumptions!C28 -> 704.73191 | H11: =('Cash Flow Statement'!D14*(1/(1+0.095)^1)+'Cash Flow Statement'!E14*(1/(1+0.095)^2)+'Cash Flow Statement'!F14*(1/(1+0.095)^3)+'Cash Flow Statement'!G14*(1/(1+0.095)^4)+'Cash Flow Statement'!H14*(1/(1+0.095)^5)+('Income Statement'!H16*30)/(1+0.095)^5-Assumptions!C29)/Assumptions!C28 -> 750.03775 | I11: =('Cash Flow Statement'!D14*(1/(1+0.095)^1)+'Cash Flow Statement'!E14*(1/(1+0.095)^2)+'Cash Flow Statement'!F14*(1/(1+0.095)^3)+'Cash Flow Statement'!G14*(1/(1+0.095)^4)+'Cash Flow Statement'!H14*(1/(1+0.095)^5)+('Income Statement'!H16*32)/(1+0.095)^5-Assumptions!C29)/Assumptions!C28 -> 795.34359 | J11: =('Cash Flow Statement'!D14*(1/(1+0.095)^1)+'Cash Flow Statement'!E14*(1/(1+0.095)^2)+'Cash Flow Statement'!F14*(1/(1+0.095)^3)+'Cash Flow Statement'!G14*(1/(1+0.095)^4)+'Cash Flow Statement'!H14*(1/(1+0.095)^5)+('Income Statement'!H16*34)/(1+0.095)^5-Assumptions!C29)/Assumptions!C28 -> 840.64943
B12: 10.0% | C12: =('Cash Flow Statement'!D14*(1/(1+0.1)^1)+'Cash Flow Statement'!E14*(1/(1+0.1)^2)+'Cash Flow Statement'!F14*(1/(1+0.1)^3)+'Cash Flow Statement'!G14*(1/(1+0.1)^4)+'Cash Flow Statement'!H14*(1/(1+0.1)^5)+('Income Statement'!H16*20)/(1+0.1)^5-Assumptions!C29)/Assumptions!C28 -> 512.35059 | D12: =('Cash Flow Statement'!D14*(1/(1+0.1)^1)+'Cash Flow Statement'!E14*(1/(1+0.1)^2)+'Cash Flow Statement'!F14*(1/(1+0.1)^3)+'Cash Flow Statement'!G14*(1/(1+0.1)^4)+'Cash Flow Statement'!H14*(1/(1+0.1)^5)+('Income Statement'!H16*22)/(1+0.1)^5-Assumptions!C29)/Assumptions!C28 -> 556.63607 | E12: =('Cash Flow Statement'!D14*(1/(1+0.1)^1)+'Cash Flow Statement'!E14*(1/(1+0.1)^2)+'Cash Flow Statement'!F14*(1/(1+0.1)^3)+'Cash Flow Statement'!G14*(1/(1+0.1)^4)+'Cash Flow Statement'!H14*(1/(1+0.1)^5)+('Income Statement'!H16*24)/(1+0.1)^5-Assumptions!C29)/Assumptions!C28 -> 600.92155 | F12: =('Cash Flow Statement'!D14*(1/(1+0.1)^1)+'Cash Flow Statement'!E14*(1/(1+0.1)^2)+'Cash Flow Statement'!F14*(1/(1+0.1)^3)+'Cash Flow Statement'!G14*(1/(1+0.1)^4)+'Cash Flow Statement'!H14*(1/(1+0.1)^5)+('Income Statement'!H16*26)/(1+0.1)^5-Assumptions!C29)/Assumptions!C28 -> 645.20703 | G12: =('Cash Flow Statement'!D14*(1/(1+0.1)^1)+'Cash Flow Statement'!E14*(1/(1+0.1)^2)+'Cash Flow Statement'!F14*(1/(1+0.1)^3)+'Cash Flow Statement'!G14*(1/(1+0.1)^4)+'Cash Flow Statement'!H14*(1/(1+0.1)^5)+('Income Statement'!H16*28)/(1+0.1)^5-Assumptions!C29)/Assumptions!C28 -> 689.49251 | H12: =('Cash Flow Statement'!D14*(1/(1+0.1)^1)+'Cash Flow Statement'!E14*(1/(1+0.1)^2)+'Cash Flow Statement'!F14*(1/(1+0.1)^3)+'Cash Flow Statement'!G14*(1/(1+0.1)^4)+'Cash Flow Statement'!H14*(1/(1+0.1)^5)+('Income Statement'!H16*30)/(1+0.1)^5-Assumptions!C29)/Assumptions!C28 -> 733.77799 | I12: =('Cash Flow Statement'!D14*(1/(1+0.1)^1)+'Cash Flow Statement'!E14*(1/(1+0.1)^2)+'Cash Flow Statement'!F14*(1/(1+0.1)^3)+'Cash Flow Statement'!G14*(1/(1+0.1)^4)+'Cash Flow Statement'!H14*(1/(1+0.1)^5)+('Income Statement'!H16*32)/(1+0.1)^5-Assumptions!C29)/Assumptions!C28 -> 778.06347 | J12: =('Cash Flow Statement'!D14*(1/(1+0.1)^1)+'Cash Flow Statement'!E14*(1/(1+0.1)^2)+'Cash Flow Statement'!F14*(1/(1+0.1)^3)+'Cash Flow Statement'!G14*(1/(1+0.1)^4)+'Cash Flow Statement'!H14*(1/(1+0.1)^5)+('Income Statement'!H16*34)/(1+0.1)^5-Assumptions!C29)/Assumptions!C28 -> 822.34895
B13: 10.5% | C13: =('Cash Flow Statement'!D14*(1/(1+0.105)^1)+'Cash Flow Statement'!E14*(1/(1+0.105)^2)+'Cash Flow Statement'!F14*(1/(1+0.105)^3)+'Cash Flow Statement'!G14*(1/(1+0.105)^4)+'Cash Flow Statement'!H14*(1/(1+0.105)^5)+('Income Statement'!H16*20)/(1+0.105)^5-Assumptions!C29)/Assumptions!C28 -> 501.48753 | D13: =('Cash Flow Statement'!D14*(1/(1+0.105)^1)+'Cash Flow Statement'!E14*(1/(1+0.105)^2)+'Cash Flow Statement'!F14*(1/(1+0.105)^3)+'Cash Flow Statement'!G14*(1/(1+0.105)^4)+'Cash Flow Statement'!H14*(1/(1+0.105)^5)+('Income Statement'!H16*22)/(1+0.105)^5-Assumptions!C29)/Assumptions!C28 -> 544.7801 | E13: =('Cash Flow Statement'!D14*(1/(1+0.105)^1)+'Cash Flow Statement'!E14*(1/(1+0.105)^2)+'Cash Flow Statement'!F14*(1/(1+0.105)^3)+'Cash Flow Statement'!G14*(1/(1+0.105)^4)+'Cash Flow Statement'!H14*(1/(1+0.105)^5)+('Income Statement'!H16*24)/(1+0.105)^5-Assumptions!C29)/Assumptions!C28 -> 588.07267 | F13: =('Cash Flow Statement'!D14*(1/(1+0.105)^1)+'Cash Flow Statement'!E14*(1/(1+0.105)^2)+'Cash Flow Statement'!F14*(1/(1+0.105)^3)+'Cash Flow Statement'!G14*(1/(1+0.105)^4)+'Cash Flow Statement'!H14*(1/(1+0.105)^5)+('Income Statement'!H16*26)/(1+0.105)^5-Assumptions!C29)/Assumptions!C28 -> 631.36524 | G13: =('Cash Flow Statement'!D14*(1/(1+0.105)^1)+'Cash Flow Statement'!E14*(1/(1+0.105)^2)+'Cash Flow Statement'!F14*(1/(1+0.105)^3)+'Cash Flow Statement'!G14*(1/(1+0.105)^4)+'Cash Flow Statement'!H14*(1/(1+0.105)^5)+('Income Statement'!H16*28)/(1+0.105)^5-Assumptions!C29)/Assumptions!C28 -> 674.65782 | H13: =('Cash Flow Statement'!D14*(1/(1+0.105)^1)+'Cash Flow Statement'!E14*(1/(1+0.105)^2)+'Cash Flow Statement'!F14*(1/(1+0.105)^3)+'Cash Flow Statement'!G14*(1/(1+0.105)^4)+'Cash Flow Statement'!H14*(1/(1+0.105)^5)+('Income Statement'!H16*30)/(1+0.105)^5-Assumptions!C29)/Assumptions!C28 -> 717.95039 | I13: =('Cash Flow Statement'!D14*(1/(1+0.105)^1)+'Cash Flow Statement'!E14*(1/(1+0.105)^2)+'Cash Flow Statement'!F14*(1/(1+0.105)^3)+'Cash Flow Statement'!G14*(1/(1+0.105)^4)+'Cash Flow Statement'!H14*(1/(1+0.105)^5)+('Income Statement'!H16*32)/(1+0.105)^5-Assumptions!C29)/Assumptions!C28 -> 761.24296 | J13: =('Cash Flow Statement'!D14*(1/(1+0.105)^1)+'Cash Flow Statement'!E14*(1/(1+0.105)^2)+'Cash Flow Statement'!F14*(1/(1+0.105)^3)+'Cash Flow Statement'!G14*(1/(1+0.105)^4)+'Cash Flow Statement'!H14*(1/(1+0.105)^5)+('Income Statement'!H16*34)/(1+0.105)^5-Assumptions!C29)/Assumptions!C28 -> 804.53553
B14: 11.0% | C14: =('Cash Flow Statement'!D14*(1/(1+0.11)^1)+'Cash Flow Statement'!E14*(1/(1+0.11)^2)+'Cash Flow Statement'!F14*(1/(1+0.11)^3)+'Cash Flow Statement'!G14*(1/(1+0.11)^4)+'Cash Flow Statement'!H14*(1/(1+0.11)^5)+('Income Statement'!H16*20)/(1+0.11)^5-Assumptions!C29)/Assumptions!C28 -> 490.91023 | D14: =('Cash Flow Statement'!D14*(1/(1+0.11)^1)+'Cash Flow Statement'!E14*(1/(1+0.11)^2)+'Cash Flow Statement'!F14*(1/(1+0.11)^3)+'Cash Flow Statement'!G14*(1/(1+0.11)^4)+'Cash Flow Statement'!H14*(1/(1+0.11)^5)+('Income Statement'!H16*22)/(1+0.11)^5-Assumptions!C29)/Assumptions!C28 -> 533.23648 | E14: =('Cash Flow Statement'!D14*(1/(1+0.11)^1)+'Cash Flow Statement'!E14*(1/(1+0.11)^2)+'Cash Flow Statement'!F14*(1/(1+0.11)^3)+'Cash Flow Statement'!G14*(1/(1+0.11)^4)+'Cash Flow Statement'!H14*(1/(1+0.11)^5)+('Income Statement'!H16*24)/(1+0.11)^5-Assumptions!C29)/Assumptions!C28 -> 575.56274 | F14: =('Cash Flow Statement'!D14*(1/(1+0.11)^1)+'Cash Flow Statement'!E14*(1/(1+0.11)^2)+'Cash Flow Statement'!F14*(1/(1+0.11)^3)+'Cash Flow Statement'!G14*(1/(1+0.11)^4)+'Cash Flow Statement'!H14*(1/(1+0.11)^5)+('Income Statement'!H16*26)/(1+0.11)^5-Assumptions!C29)/Assumptions!C28 -> 617.889 | G14: =('Cash Flow Statement'!D14*(1/(1+0.11)^1)+'Cash Flow Statement'!E14*(1/(1+0.11)^2)+'Cash Flow Statement'!F14*(1/(1+0.11)^3)+'Cash Flow Statement'!G14*(1/(1+0.11)^4)+'Cash Flow Statement'!H14*(1/(1+0.11)^5)+('Income Statement'!H16*28)/(1+0.11)^5-Assumptions!C29)/Assumptions!C28 -> 660.21526 | H14: =('Cash Flow Statement'!D14*(1/(1+0.11)^1)+'Cash Flow Statement'!E14*(1/(1+0.11)^2)+'Cash Flow Statement'!F14*(1/(1+0.11)^3)+'Cash Flow Statement'!G14*(1/(1+0.11)^4)+'Cash Flow Statement'!H14*(1/(1+0.11)^5)+('Income Statement'!H16*30)/(1+0.11)^5-Assumptions!C29)/Assumptions!C28 -> 702.54152 | I14: =('Cash Flow Statement'!D14*(1/(1+0.11)^1)+'Cash Flow Statement'!E14*(1/(1+0.11)^2)+'Cash Flow Statement'!F14*(1/(1+0.11)^3)+'Cash Flow Statement'!G14*(1/(1+0.11)^4)+'Cash Flow Statement'!H14*(1/(1+0.11)^5)+('Income Statement'!H16*32)/(1+0.11)^5-Assumptions!C29)/Assumptions!C28 -> 744.86778 | J14: =('Cash Flow Statement'!D14*(1/(1+0.11)^1)+'Cash Flow Statement'!E14*(1/(1+0.11)^2)+'Cash Flow Statement'!F14*(1/(1+0.11)^3)+'Cash Flow Statement'!G14*(1/(1+0.11)^4)+'Cash Flow Statement'!H14*(1/(1+0.11)^5)+('Income Statement'!H16*34)/(1+0.11)^5-Assumptions!C29)/Assumptions!C28 -> 787.19404
B18: TABLE 2: Share Price Sensitivity — Revenue Growth Rate vs. WACC
B19: Rev Growth ↓ / WACC → | C19: 7.5% | D19: 8.0% | E19: 8.5% | F19: 9.0% | G19: 9.5% | H19: 10.0% | I19: 10.5% | J19: 11.0%
B20: 8% | C20: 554.67 | D20: 542.54 | E20: 530.73 | F20: 519.25 | G20: 508.07 | H20: 497.18 | I20: 486.59 | J20: 476.28
B21: 10% | C21: 605.16 | D21: 591.88 | E21: 578.97 | F21: 566.4 | G21: 554.17 | H21: 542.27 | I21: 530.68 | J21: 519.4
B22: 12% | C22: 659.37 | D22: 644.88 | E22: 630.77 | F22: 617.04 | G22: 603.68 | H22: 590.68 | I22: 578.03 | J22: 565.7
B23: 14% | C23: 717.52 | D23: 701.71 | E23: 686.33 | F23: 671.35 | G23: 656.78 | H23: 642.6 | I23: 628.8 | J23: 615.36
B24: 15% | C24: 748.14 | D24: 731.63 | E24: 715.57 | F24: 699.95 | G24: 684.74 | H24: 669.94 | I24: 655.53 | J24: 641.5
B25: 16% | C25: 779.82 | D25: 762.6 | E25: 745.84 | F25: 729.54 | G25: 713.67 | H25: 698.22 | I25: 683.19 | J25: 668.55
B26: 18% | C26: 846.48 | D26: 827.75 | E26: 809.53 | F26: 791.79 | G26: 774.53 | H26: 757.74 | I26: 741.39 | J26: 725.47
B27: 20% | C27: 917.74 | D27: 897.39 | E27: 877.6 | F27: 858.34 | G27: 839.59 | H27: 821.35 | I27: 803.59 | J27: 786.3
B31: TABLE 3: Share Price Sensitivity — COGS % of Revenue vs. EV/EBITDA Multiple
B32: COGS % ↓ / EV/EBITDA → | C32: 20x | D32: 22x | E32: 24x | F32: 26x | G32: 28x | H32: 30x | I32: 32x | J32: 34x
B33: 28% | C33: 558.18 | D33: 606.45 | E33: 654.73 | F33: 703 | G33: 751.27 | H33: 799.55 | I33: 847.82 | J33: 896.09
B34: 30% | C34: 538.31 | D34: 584.9 | E34: 631.48 | F34: 678.07 | G34: 724.66 | H34: 771.25 | I34: 817.84 | J34: 864.43
B35: 31% | C35: 528.37 | D35: 574.12 | E35: 619.86 | F35: 665.61 | G35: 711.35 | H35: 757.1 | I35: 802.85 | J35: 848.59
B36: 32% | C36: 518.43 | D36: 563.34 | E36: 608.24 | F36: 653.14 | G36: 698.05 | H36: 742.95 | I36: 787.85 | J36: 832.76
B37: 33% | C37: 508.5 | D37: 552.56 | E37: 596.62 | F37: 640.68 | G37: 684.74 | H37: 728.8 | I37: 772.86 | J37: 816.92
B38: 34% | C38: 498.56 | D38: 541.78 | E38: 585 | F38: 628.22 | G38: 671.43 | H38: 714.65 | I38: 757.87 | J38: 801.09
B39: 35% | C39: 488.62 | D39: 531 | E39: 573.38 | F39: 615.75 | G39: 658.13 | H39: 700.5 | I39: 742.88 | J39: 785.26
B40: 37% | C40: 468.75 | D40: 509.44 | E40: 550.13 | F40: 590.82 | G40: 631.51 | H40: 672.21 | I40: 712.9 | J40: 753.59
B43: 🔴 Low share price 🟡 Mid-range 🟢 High share price ⬛ = Base case (amber highlight)

Sheet Charts & Visualizations
A1: MICROSOFT CORPORATION | CHARTS & VISUAL ANALYTICS
B4: Year | C4: Revenue ($M) | D4: EBITDA ($M) | E4: Net Income ($M) | F4: FCFF ($M) | H4: Year | I4: Gross Margin % | J4: EBITDA Margin % | K4: Net Margin %
B5: 2024 | C5: ='Income Statement'!C6 -> 245122 | D5: ='Income Statement'!C16 -> 279136 | E5: ='Income Statement'!C21 -> 212145.81 | F5: ='Cash Flow Statement'!C14 -> 181029.81 | H5: 2024 | I5: ='Income Statement'!C10 -> 1.3023556 | J5: =D5/C5 -> 1.1387636 | K5: ='Income Statement'!C22 -> 0.8654703
B6: 2025 | C6: ='Income Statement'!D6 -> 281890.3 | D6: ='Income Statement'!D16 -> 147146.74 | E6: ='Income Statement'!D21 -> 107430.87 | F6: ='Cash Flow Statement'!D14 -> 96880.622 | H6: 2025 | I6: ='Income Statement'!D10 -> 0.67 | J6: =D6/C6 -> 0.522 | K6: ='Income Statement'!D22 -> 0.38110878
B7: 2026 | C7: ='Income Statement'!E6 -> 326992.75 | D7: ='Income Statement'!E16 -> 174287.13 | E7: ='Income Statement'!E21 -> 126760.65 | F7: ='Cash Flow Statement'!E14 -> 113752.81 | H7: 2026 | I7: ='Income Statement'!E10 -> 0.675 | J7: =D7/C7 -> 0.533 | K7: ='Income Statement'!E22 -> 0.38765585
B8: 2027 | C8: ='Income Statement'!F6 -> 372771.73 | D8: ='Income Statement'!F16 -> 202415.05 | E8: ='Income Statement'!F21 -> 146770.45 | F8: ='Cash Flow Statement'!F14 -> 133061.72 | H8: 2027 | I8: ='Income Statement'!F10 -> 0.68 | J8: =D8/C8 -> 0.543 | K8: ='Income Statement'!F22 -> 0.39372741
B9: 2028 | C9: ='Income Statement'!G6 -> 421232.06 | D9: ='Income Statement'!G16 -> 232520.1 | E9: ='Income Statement'!G21 -> 168486.12 | F9: ='Cash Flow Statement'!G14 -> 153741.21 | H9: 2028 | I9: ='Income Statement'!G10 -> 0.685 | J9: =D9/C9 -> 0.552 | K9: ='Income Statement'!G22 -> 0.39998408
B10: 2029 | C10: ='Income Statement'!H6 -> 471779.9 | D10: ='Income Statement'!H16 -> 265140.31 | E10: ='Income Statement'!H21 -> 191727.01 | F10: ='Cash Flow Statement'!H14 -> 176574.44 | H10: 2029 | I10: ='Income Statement'!H10 -> 0.69 | J10: =D10/C10 -> 0.562 | K10: ='Income Statement'!H22 -> 0.40639078
B18: Year | C18: FCFF ($M)
B19: 2024 | C19: ='Cash Flow Statement'!C14 -> 181029.81
B20: 2025 | C20: ='Cash Flow Statement'!D14 -> 96880.622
B21: 2026 | C21: ='Cash Flow Statement'!E14 -> 113752.81
B22: 2027 | C22: ='Cash Flow Statement'!F14 -> 133061.72
B23: 2028 | C23: ='Cash Flow Statement'!G14 -> 153741.21
B24: 2029 | C24: ='Cash Flow Statement'!H14 -> 176574.44

Sheet Tornado Analysis
A1: MICROSOFT CORPORATION | TORNADO SENSITIVITY CHART | Impact on Share Price
A2: Shows the range of implied share price when each driver is stressed ±1 standard deviation from base case. Wider bars = greater sensitivity.
B4: Driver | C4: Bear Case Input | D4: Bear SP ($) | E4: Base SP ($) | F4: Bull SP ($) | G4: Bull Case Input | H4: SP Range ($) | I4: Bear SP ($)
B5: Revenue Growth Rate | C5: 10.0% | D5: 554.17 | E5: 684.74 | F5: 839.59 | G5: 20.0% | H5: 285.42 | I5: =-D5 -> -554.17
B6: EV/EBITDA Multiple | C6: 22x | D6: 552.56 | E6: 684.74 | F6: 816.92 | G6: 34x | H6: 264.36 | I6: =-D6 -> -552.56
B7: COGS % of Revenue | C7: 37.0% | D7: 631.51 | E7: 684.74 | F7: 751.27 | G7: 28.0% | H7: 119.76 | I7: =-D7 -> -631.51
B8: WACC | C8: 11.0% | D8: 641.5 | E8: 684.74 | F8: 748.14 | G8: 7.5% | H8: 106.64 | I8: =-D8 -> -641.5
B9: Terminal Growth Rate | C9: 1.5% | D9: 684.74 | E9: 684.74 | F9: 684.74 | G9: 4.0% | H9: 0 | I9: =-D9 -> -684.74
J21: 0.15
J22: 28
B27: Revenue Growth rate +/- 5% | E27: COGS +/-5% | H27: EV/EBITDA +/1 | L27: WACC +/- 1% | O27: Terminal Growth Rate +/2%
B28: 0 | C28: ='DCF Valuation'!C23 -> 704.73191 | E28: 0 | F28: ='DCF Valuation'!C23 -> 704.73191 | H28: 0 | I28: ='DCF Valuation'!C23 -> 704.73191 | L28: 0 | M28: ='DCF Valuation'!C23 -> 704.73191 | O28: 0 | P28: ='DCF Valuation'!C23 -> 704.73191
B29: 0.05 | C29: 865.67957 | E29: 0.05 | F29: 640.82745 | H29: 2 | I29: 750.03775 | L29: 0.01 | M29: 674.65782 | O29: 0.02 | P29: 704.73191
B30: -0.05 | C30: 569.22978 | E30: -0.05 | F30: 768.63637 | H30: -2 | I30: 659.42607 | L30: -0.01 | M30: 736.47739 | O30: -0.02 | P30: 704.73191
B32: ='DCF Valuation'!C23 -> 704.73191 | C32: 0.05 | D32: 0.1 | E32: 0.15 | F32: 0.2 | G32: 0.25
B33: 24 | C33: 398.75035 | D33: 496.82342 | E33: 614.12023 | F33: 753.37214 | G33: 917.55898
B34: 26 | C34: 427.3765 | D34: 533.0266 | E34: 659.42607 | F34: 809.52586 | G34: 986.54549
B35: 28 | C35: 456.00265 | D35: 569.22978 | E35: 704.73191 | F35: 865.67957 | G35: 1055.532
B36: 30 | C36: 484.6288 | D36: 605.43296 | E36: 750.03775 | F36: 921.83328 | G36: 1124.5185
B37: 32 | C37: 513.25495 | D37: 641.63614 | E37: 795.34359 | F37: 977.987 | G37: 1193.505
D40: Pos | G40: Neg
B41: =B27 -> Revenue Growth rate +/- 5% | C41: =C29/C28-1 -> 0.2283814 | D41: =ABS(C41) -> 0.2283814 | E41: 1 | F41: =SMALL($D$41:$D$44,E41) -> 0.042674514 | G41: {=-ABS(D41:D44)} -> -0.2283814
B42: =E27 -> COGS +/-5% | C42: =F29/F28-1 -> -0.090679108 | D42: =ABS(C42) -> 0.090679108 | E42: 2 | F42: =SMALL($D$41:$D$44,E42) -> 0.064288049 | G42: -0.090679108
B43: =H27 -> EV/EBITDA +/1 | C43: =I29/I28-1 -> 0.064288049 | D43: =ABS(C43) -> 0.064288049 | E43: 3 | F43: =SMALL($D$41:$D$44,E43) -> 0.090679108 | G43: -0.064288049
B44: =L27 -> WACC +/- 1% | C44: =M29/M28-1 -> -0.042674514 | D44: =ABS(C44) -> 0.042674514 | E44: 4 | F44: =SMALL($D$41:$D$44,E44) -> 0.2283814 | G44: -0.042674514

Sheet Sheet1
